gi_cli/__init__.py
gi_cli/__main__.py
gi_cli/config.py
gi_cli/constants.py
gi_cli/functions.py
gi_cli-0.0.4.dist-info/entry_points.txt
gi_cli-0.0.4.dist-info/LICENSE
gi_cli-0.0.4.dist-info/WHEEL
gi_cli-0.0.4.dist-info/METADATA
gi_cli-0.0.4.dist-info/RECORD
