Metadata-Version: 2.1
Name: gi-cli
Version: 0.0.4
Summary: CLI to easily create .gitignore files
Home-page: https://github.com/ninest/gi/
License: MIT
Author: ninest
Requires-Python: >=3.7,<4.0
Classifier: License :: OSI Approved :: MIT License
Classifier: Programming Language :: Python :: 3
Classifier: Programming Language :: Python :: 3.7
Classifier: Programming Language :: Python :: 3.8
Classifier: Programming Language :: Python :: 3.9
Requires-Dist: python-dotenv (>=0.15.0,<0.16.0)
Requires-Dist: requests (>=2.25.1,<3.0.0)
Project-URL: Documentation, https://github.com/ninest/gi/
Project-URL: Repository, https://github.com/ninest/gi/
